lofty/__init__.py
lofty/aws_cognito_idp.py
lofty/client.py
lofty/client_auth.py
lofty/constants.py
lofty/pagination_options.py
lofty/responses/__init__.py
lofty/responses/auth/__init__.py
lofty/responses/auth/aws_credentials.py
lofty/responses/auth/device_metadata.py
lofty/responses/auth/sign_in_response.py
lofty_api-1.0.0.dist-info/LICENSE
lofty_api-1.0.0.dist-info/METADATA
lofty_api-1.0.0.dist-info/WHEEL
lofty_api-1.0.0.dist-info/top_level.txt
lofty_api-1.0.0.dist-info/RECORD
